ntypo/__init__.py
ntypo/cli.py
ntypo/words.txt
ntypo-2.1.0.dist-info/METADATA
ntypo-2.1.0.dist-info/WHEEL
ntypo-2.1.0.dist-info/entry_points.txt
ntypo-2.1.0.dist-info/top_level.txt
ntypo-2.1.0.dist-info/RECORD
