Metadata-Version: 2.4
Name: ntypo
Version: 2.1.0
Summary: A terminal typing speed test built with ncurses
Author: Eren Öğrül
Author-email: termapp@pm.me
Classifier: Programming Language :: Python :: 3
Classifier: Environment :: Console
Classifier: License :: OSI Approved :: GNU General Public License v3 (GPLv3)
Classifier: Operating System :: OS Independent
Requires-Python: >=3.8
Dynamic: author
Dynamic: author-email
Dynamic: classifier
Dynamic: description
Dynamic: description-content-type
Dynamic: requires-python
Dynamic: summary
